optimod/__init__.py
optimod/optimod.py
optimod-0.1.3.dist-info/METADATA
optimod-0.1.3.dist-info/WHEEL
optimod-0.1.3.dist-info/entry_points.txt
optimod-0.1.3.dist-info/RECORD
