Metadata-Version: 2.1
Name: optimod
Version: 0.1.3
Summary: 
Author: Mehmetcan Oralalp
Author-email: 138567742+mehmetcan-oralalp@users.noreply.github.com
Requires-Python: >=3.9,<4.0
Classifier: Programming Language :: Python :: 3
Classifier: Programming Language :: Python :: 3.9
Classifier: Programming Language :: Python :: 3.10
Classifier: Programming Language :: Python :: 3.11
Classifier: Programming Language :: Python :: 3.12
